liveness_detector/__init__.py
liveness_detector/protocol_handler.py
liveness_detector/server_launcher.py
liveness_detector/transport.py
liveness_detector/unix_socket_transport.py
liveness_detector/fonts/DejaVuSans.ttf
liveness_detector/gestures/How_To_Gestures_Readme.md
liveness_detector/gestures/blink.json
liveness_detector/gestures/downup.json
liveness_detector/gestures/eyesDownwards.json
liveness_detector/gestures/eyesShiftLeft.json
liveness_detector/gestures/eyesShiftRight.json
liveness_detector/gestures/eyesUpwards.json
liveness_detector/gestures/faceFrontLeft.json
liveness_detector/gestures/faceFrontRight.json
liveness_detector/gestures/gesturesSchema.py
liveness_detector/gestures/openCloseMouth.json
liveness_detector/gestures/smile.json
liveness_detector/gestures/updown.json
liveness_detector/gestures/icons/openclousemouth.png
liveness_detector/gestures/icons/sample.png
liveness_detector/gestures/locales/default.json
liveness_detector/gestures/locales/en.json
liveness_detector/gestures/locales/es.json
liveness_detector/model/face_landmarker.task
liveness_detector/model/glasses_model.onnx
liveness_detector/model/haarcascade_frontalface_default.xml
liveness_detector/server/livenessDetectorServer
liveness_detector/server/lib/libHalf.so.12
liveness_detector/server/lib/libIex-2_2.so.12
liveness_detector/server/lib/libIexMath-2_2.so.12
liveness_detector/server/lib/libIlmImf-2_2.so.22
liveness_detector/server/lib/libIlmThread-2_2.so.12
liveness_detector/server/lib/libImath-2_2.so.12
liveness_detector/server/lib/libjbig.so.2.1
liveness_detector/server/lib/libjpeg.so.62
liveness_detector/server/lib/libopenjp2.so.7
liveness_detector/server/lib/libpng16.so.16
liveness_detector/server/lib/libtiff.so.5
liveness_detector/server/lib/libwebp.so.7
liveness_detector/server/lib/libz.so.1
liveness_detector-0.7.0.dist-info/METADATA
liveness_detector-0.7.0.dist-info/WHEEL
liveness_detector-0.7.0.dist-info/entry_points.txt
liveness_detector-0.7.0.dist-info/top_level.txt
liveness_detector-0.7.0.dist-info/RECORD
