Metadata-Version: 2.4
Name: liveness_detector
Version: 0.7.0
Summary: Liveness detector server launcher with precompiled binaries
Author: 2060.io
Author-email: r@2060.io
Classifier: Programming Language :: Python :: 3
Classifier: Operating System :: OS Independent
Requires-Python: >=3.6
Dynamic: author
Dynamic: author-email
Dynamic: classifier
Dynamic: description
Dynamic: description-content-type
Dynamic: requires-python
Dynamic: summary
